{"title":"我的数学启蒙","date":"2018-03-25T10:01:43.000Z","excerpt":"","slug":"我的数学启蒙","comments":true,"tags":["闲谈","数学"],"categories":["闲谈"],"updated":"2018-03-25T10:25:19.973Z","content":"<h1 id=\"1-学习数学\"><a href=\"#1-学习数学\" class=\"headerlink\" title=\"1 学习数学\"></a>1 学习数学</h1><h2 id=\"1-1-开始认识\"><a href=\"#1-1-开始认识\" class=\"headerlink\" title=\"1.1 开始认识\"></a>1.1 开始认识</h2><p>数学，这个词我第一次接触是在小学时候，一年级的时候有了这门课，1+1=2，我学会的第一道数学题。此时我对数学并没有什么认识，一门课程而已，老师第二天会检查课后作业，还是得想办法应对的呀！</p>\n<p>放学后书包往床上一扔，撒腿准备跑去玩，“作业做完了没？”，老爸的脸上没什么表情，不怒自威，我只好低着头乖乖坐在桌子前面，恶狠狠的拿出数学作业，心想着“数学太坏了，恨死它了”，心不在焉的做着数学作业。</p>\n<h2 id=\"1-2-有点喜欢\"><a href=\"#1-2-有点喜欢\" class=\"headerlink\" title=\"1.2 有点喜欢\"></a>1.2 有点喜欢</h2><p>就这样每天放学回家，被老爸逼着做数学作业，一学期、两学期…… 效果大概是上课老师讲课提问的时候，别的小孩需要思考一下题目，而我好像可以比他们快那么一丢丢。当然这都是被我忽略了，那些本来可以玩耍的下午，都被数学占了。</p>\n<p>三年级了，不知不觉“认识数学”已经三年了，期中考试数学成绩99分，额…差一分满分，但也是我一直以来得的最高分了，被老师叫到讲台上当着全班同学的面夸了一下，心里美滋滋，想一下放学回家，把这个好消息告诉爸妈。我想我大概有点喜欢数学了。</p>\n<p>continue…</p>\n","next":{"title":"Hello World","slug":"hello-world"}}